{
  "1": "1",
  "2": "2",
  "3": "2",
  "4": "2",
  "5": "2",
  "6": "2",
  "7": "7",
  "8": "7",
  "9": "7",
  "0": "7",
  "-": "7",
  "=": "7",

  "q": "2",
  "w": "2",
  "e": "2",
  "r": "3",
  "t": "3",
  "y": "3",
  "u": "7",
  "i": "7",
  "o": "7",
  "p": "7",

  "a": "1",
  "s": "2",
  "d": "3",
  "f": "3",
  "g": "3",
  "h": "6",
  "j": "6",
  "k": "6",
  "l": "7",
  ";": "7",

  "z": "1",
  "x": "1",
  "c": "3",
  "v": "3",
  "b": "3",
  "n": "6",
  "m": "6",
  ".": "6",

  "!": "1",
  "@": "2",
  "#": "3",
  "$": "3",
  "%": "3",
  "^": "3",
  "&": "3",
  "*": "6",
  "(": "6",
  ")": "7",
  "+": "7",

  ":": "6",

  "?": "8"
}
